Metadata-Version: 2.1
Name: converterjson
Version: 0.0.1
Summary: Json to tree Hierarchy converter
Author: PavanPawar
Author-email: pppawar124@gmail.com
Keywords: json,graph,nodeId,child,name
Classifier: Development Status :: 1 - Planning
Classifier: Intended Audience :: Developers
Classifier: Programming Language :: Python :: 3
Classifier: Operating System :: OS Independent
Requires-Python: >=3.6, <4
License-File: LICENSE.txt
